dj_currencies/__init__.py
dj_currencies/admin.py
dj_currencies/apis.py
dj_currencies/apps.py
dj_currencies/backends.py
dj_currencies/exceptions.py
dj_currencies/factories.py
dj_currencies/management/__init__.py
dj_currencies/management/commands/__init__.py
dj_currencies/management/commands/update_exchange_rates.py
dj_currencies/migrations/0001_initial.py
dj_currencies/migrations/0002_auto_20180429_2228.py
dj_currencies/migrations/0003_auto_20200908_2321.py
dj_currencies/migrations/__init__.py
dj_currencies/models.py
dj_currencies/settings.py
dj_currencies/sources.py
dj_currencies-1.1.0.dist-info/WHEEL
dj_currencies-1.1.0.dist-info/LICENSE
dj_currencies-1.1.0.dist-info/METADATA
dj_currencies-1.1.0.dist-info/RECORD
