Metadata-Version: 2.1
Name: dj-currencies
Version: 1.1.0
Summary: A reusable Django app that integrates https://openexchangerates.org/
Home-page: https://github.com/CoverGenius/dj-currencies
License: MIT
Keywords: currency,openexchangerates,django
Author: Lihan
Author-email: lihan@covergenius.com
Maintainer: Lihan Li
Maintainer-email: lihan@covergenius.com
Requires-Python: >=3.8,<4.0
Classifier: Development Status :: 5 - Production/Stable
Classifier: Framework :: Django :: 3.0
Classifier: Framework :: Django :: 4.0
Classifier: Intended Audience :: Developers
Classifier: License :: OSI Approved :: MIT License
Classifier: Natural Language :: English
Classifier: Programming Language :: Python :: 3
Classifier: Programming Language :: Python :: 3.8
Classifier: Programming Language :: Python :: 3.9
Classifier: Programming Language :: Python :: 3.10
Classifier: Programming Language :: Python :: 3.11
Classifier: Programming Language :: Python :: 3.10
Classifier: Programming Language :: Python :: 3.11
Classifier: Programming Language :: Python :: 3.8
Classifier: Programming Language :: Python :: 3.9
Requires-Dist: django (>=3.2,<5.0)
Requires-Dist: psycopg2-binary (>=2.7,<4.0)
Project-URL: Documentation, https://dj-currencies.readthedocs.io
Project-URL: Repository, https://github.com/CoverGenius/dj-currencies
